model_inspector/__init__.py
model_inspector/_modidx.py
model_inspector/_nbdev.py
model_inspector/class_utils.py
model_inspector/delegate.py
model_inspector/explore.py
model_inspector/get_inspector.py
model_inspector/tune.py
model_inspector/inspect/__init__.py
model_inspector/inspect/any_model.py
model_inspector/inspect/classifier.py
model_inspector/inspect/linear_model.py
model_inspector/inspect/regressor.py
model_inspector/inspect/searchcv_estimator.py
model_inspector/inspect/testing.py
model_inspector/inspect/tree.py
model_inspector-0.27.4.dist-info/LICENSE
model_inspector-0.27.4.dist-info/METADATA
model_inspector-0.27.4.dist-info/WHEEL
model_inspector-0.27.4.dist-info/entry_points.txt
model_inspector-0.27.4.dist-info/top_level.txt
model_inspector-0.27.4.dist-info/RECORD
