Metadata-Version: 2.1
Name: model-inspector
Version: 0.27.4
Summary: Inspect machine learning models
Home-page: https://github.com/gsganden/model_inspector/
Author: Greg Gandenberger
Author-email: gsganden@gmail.com
License: Apache Software License 2.0
Keywords: machine-learning
Classifier: Development Status :: 4 - Beta
Classifier: Intended Audience :: Developers
Classifier: Natural Language :: English
Classifier: Programming Language :: Python :: 3.7
Classifier: Programming Language :: Python :: 3.8
Classifier: Programming Language :: Python :: 3.9
Classifier: Programming Language :: Python :: 3.10
Classifier: License :: OSI Approved :: Apache Software License
Requires-Python: >=3.7
License-File: LICENSE
Requires-Dist: catboost
Requires-Dist: fastcore
Requires-Dist: IPython (>7)
Requires-Dist: matplotlib (>=3.4.2)
Requires-Dist: numpy
Requires-Dist: pandas
Requires-Dist: scikit-learn (>=0.24)
Requires-Dist: scipy
Requires-Dist: seaborn
Requires-Dist: tqdm
Requires-Dist: waterfallcharts
Provides-Extra: dev
Requires-Dist: black ; extra == 'dev'
Requires-Dist: flake8 ; extra == 'dev'
Requires-Dist: ipdb ; extra == 'dev'
Requires-Dist: jinja2 ; extra == 'dev'
Requires-Dist: jupyterlab ; extra == 'dev'
Requires-Dist: nbdev ; extra == 'dev'
Requires-Dist: nbqa ; extra == 'dev'
Requires-Dist: twine ; extra == 'dev'
